{
  "league": "Men's Division 1",
  "fileName": "mens-division-1",
  "teams": [
    {
      "league": "Men's Division 1",
      "teamId": "320",
      "teamName": "Galway D1M",
      "logoUrl": "https://images.dataproject.com/vir/TeamLogo/40/30/TeamLogo_320.jpg",
      "rankingPoints": 20,
      "matches": {
        "played": 12,
        "won": 6,
        "lost": 6
      },
      "sets": {
        "won": 27,
        "lost": 22,
        "ratio": 1.23
      },
      "points": {
        "won": 1075,
        "lost": 1042,
        "ratio": 1.032
      },
      "resultsBreakdown": {
        "wins3_0": 3,
        "wins3_1": 2,
        "wins3_2": 1,
        "losses2_3": 3,
        "losses1_3": 3,
        "losses0_3": 0
      },
      "penalty": null,
      "position": 1
    },
    {
      "league": "Men's Division 1",
      "teamId": "321",
      "teamName": "Munster Thunder D1M",
      "logoUrl": "https://images.dataproject.com/vir/TeamLogo/40/30/TeamLogo_321.jpg",
      "rankingPoints": 19,
      "matches": {
        "played": 12,
        "won": 7,
        "lost": 5
      },
      "sets": {
        "won": 25,
        "lost": 23,
        "ratio": 1.09
      },
      "points": {
        "won": 1055,
        "lost": 1062,
        "ratio": 0.993
      },
      "resultsBreakdown": {
        "wins3_0": 2,
        "wins3_1": 2,
        "wins3_2": 3,
        "losses2_3": 1,
        "losses1_3": 2,
        "losses0_3": 2
      },
      "penalty": null,
      "position": 2
    },
    {
      "league": "Men's Division 1",
      "teamId": "349",
      "teamName": "Gardians Masters",
      "logoUrl": "https://images.dataproject.com/vir/TeamLogo/40/30/TeamLogo_349.jpg",
      "rankingPoints": 16,
      "matches": {
        "played": 12,
        "won": 5,
        "lost": 7
      },
      "sets": {
        "won": 21,
        "lost": 26,
        "ratio": 0.81
      },
      "points": {
        "won": 1022,
        "lost": 1039,
        "ratio": 0.984
      },
      "resultsBreakdown": {
        "wins3_0": 1,
        "wins3_1": 3,
        "wins3_2": 1,
        "losses2_3": 2,
        "losses1_3": 2,
        "losses0_3": 3
      },
      "penalty": null,
      "position": 3
    },
    {
      "league": "Men's Division 1",
      "teamId": "351",
      "teamName": "Aer Lingus Harriers",
      "logoUrl": "https://images.dataproject.com/vir/TeamLogo/40/30/TeamLogo_351.jpg",
      "rankingPoints": 15,
      "matches": {
        "played": 12,
        "won": 6,
        "lost": 6
      },
      "sets": {
        "won": 22,
        "lost": 26,
        "ratio": 0.85
      },
      "points": {
        "won": 1048,
        "lost": 1067,
        "ratio": 0.982
      },
      "resultsBreakdown": {
        "wins3_0": 1,
        "wins3_1": 2,
        "wins3_2": 3,
        "losses2_3": 0,
        "losses1_3": 4,
        "losses0_3": 2
      },
      "penalty": null,
      "position": 4
    },
    {
      "league": "Men's Division 1",
      "teamId": "319",
      "teamName": "Net Force D1M",
      "logoUrl": "https://images.dataproject.com/vir/TeamLogo/40/30/TeamLogo_319.jpg",
      "rankingPoints": 15,
      "matches": {
        "played": 12,
        "won": 4,
        "lost": 8
      },
      "sets": {
        "won": 21,
        "lost": 28,
        "ratio": 0.75
      },
      "points": {
        "won": 1037,
        "lost": 1087,
        "ratio": 0.954
      },
      "resultsBreakdown": {
        "wins3_0": 1,
        "wins3_1": 2,
        "wins3_2": 1,
        "losses2_3": 4,
        "losses1_3": 1,
        "losses0_3": 3
      },
      "penalty": null,
      "position": 5
    },
    {
      "league": "Men's Division 1",
      "teamId": "350",
      "teamName": "DVC D1M",
      "logoUrl": "https://images.dataproject.com/vir/TeamLogo/40/30/TeamLogo_350.jpg",
      "rankingPoints": 14,
      "matches": {
        "played": 12,
        "won": 5,
        "lost": 7
      },
      "sets": {
        "won": 25,
        "lost": 29,
        "ratio": 0.86
      },
      "points": {
        "won": 1081,
        "lost": 1123,
        "ratio": 0.963
      },
      "resultsBreakdown": {
        "wins3_0": 1,
        "wins3_1": 0,
        "wins3_2": 4,
        "losses2_3": 4,
        "losses1_3": 2,
        "losses0_3": 1
      },
      "penalty": "-1",
      "position": 6
    },
    {
      "league": "Men's Division 1",
      "teamId": "306",
      "teamName": "Ireland Men's U18",
      "logoUrl": "https://images.dataproject.com/vir/TeamLogo/40/30/TeamLogo_306.jpg",
      "rankingPoints": 4,
      "matches": {
        "played": 8,
        "won": 1,
        "lost": 7
      },
      "sets": {
        "won": 8,
        "lost": 22,
        "ratio": 0.36
      },
      "points": {
        "won": 654,
        "lost": 713,
        "ratio": 0.917
      },
      "resultsBreakdown": {
        "wins3_0": 0,
        "wins3_1": 1,
        "wins3_2": 0,
        "losses2_3": 1,
        "losses1_3": 3,
        "losses0_3": 3
      },
      "penalty": null,
      "position": 7
    }
  ],
  "updated": "2026-03-13T00:00:02.653Z",
  "totalTeams": 7,
  "lastUpdated": "2026-03-13T00:00:02.788Z",
  "dataVersion": "1.0",
  "source": "VIR Volleyball Standings"
}